pytest_mypy_testing/__init__.py
pytest_mypy_testing/message.py
pytest_mypy_testing/output_processing.py
pytest_mypy_testing/parser.py
pytest_mypy_testing/plugin.py
pytest_mypy_testing/py.typed
pytest_mypy_testing/strutil.py
pytest_mypy_testing-0.2.0.dist-info/entry_points.txt
pytest_mypy_testing-0.2.0.dist-info/licenses/LICENSES/Apache-2.0.txt
pytest_mypy_testing-0.2.0.dist-info/licenses/LICENSES/CC0-1.0.txt
pytest_mypy_testing-0.2.0.dist-info/licenses/LICENSES/MIT.txt
pytest_mypy_testing-0.2.0.dist-info/WHEEL
pytest_mypy_testing-0.2.0.dist-info/METADATA
pytest_mypy_testing-0.2.0.dist-info/RECORD
