Metadata-Version: 2.4
Name: pytest-mypy-testing
Version: 0.2.0
Summary: Pytest plugin to check mypy output
Keywords: pytest,mypy
Author-email: David Fritzsche <david.fritzsche@mvua.de>
Requires-Python: >=3.10
License-Expression: Apache-2.0 OR MIT
Classifier: Framework :: Pytest
Classifier: Intended Audience :: Developers
Classifier: Operating System :: MacOS
Classifier: Operating System :: Microsoft :: Windows
Classifier: Operating System :: OS Independent
Classifier: Operating System :: POSIX
Classifier: Programming Language :: Python :: 3.10
Classifier: Programming Language :: Python :: 3.11
Classifier: Programming Language :: Python :: 3.12
Classifier: Programming Language :: Python :: 3.13
Classifier: Programming Language :: Python :: 3.14
Classifier: Typing :: Typed
License-File: LICENSES/Apache-2.0.txt
License-File: LICENSES/CC0-1.0.txt
License-File: LICENSES/MIT.txt
Requires-Dist: pytest>=8
Requires-Dist: mypy>=1.0
Project-URL: download, https://pypi.org/project/pytest-mypy-testing/
Project-URL: github, https://github.com/davidfritzsche/pytest-mypy-testing
Project-URL: issues, https://github.com/davidfritzsche/pytest-mypy-testing/issues
